typsytex.py
typsytex-1.0.1.dist-info/LICENSE
typsytex-1.0.1.dist-info/METADATA
typsytex-1.0.1.dist-info/WHEEL
typsytex-1.0.1.dist-info/entry_points.txt
typsytex-1.0.1.dist-info/top_level.txt
typsytex-1.0.1.dist-info/RECORD
