Metadata-Version: 2.1
Name: typsytex
Version: 1.0.1
Summary: A tool that converts typst markup to an equivalent LaTeX code.
Author-email: nullst <opkdx.me@gmail.com>
License: GNU GENERAL PUBLIC LICENSE
Project-URL: homepage, https://gitlab.com/nullst/typsytex
Keywords: typst,latex
Classifier: License :: OSI Approved :: GNU General Public License v3 or later (GPLv3+)
Classifier: Intended Audience :: Developers
Classifier: Operating System :: OS Independent
Classifier: Programming Language :: Python :: 3
Classifier: Topic :: Text Processing :: Markup :: LaTeX
Requires-Python: >=3.6
License-File: LICENSE
